{
  "id": "e2e-go-linear",
  "name": "E2E Go Linear",
  "steps": [
    {
      "id": "step-a",
      "name": "Step A",
      "type": "SERVICE_TASK",
      "jobType": "go-step-a",
      "retryCount": 0,
      "nextStep": "step-b"
    },
    {
      "id": "step-b",
      "name": "Step B",
      "type": "SERVICE_TASK",
      "jobType": "go-step-b",
      "retryCount": 0,
      "nextStep": "step-c"
    },
    {
      "id": "step-c",
      "name": "Step C",
      "type": "SERVICE_TASK",
      "jobType": "go-step-c",
      "retryCount": 0,
      "nextStep": "end"
    },
    {
      "id": "end",
      "name": "End",
      "type": "END"
    }
  ]
}
