{
  "id": "e2e-node-decision-no-match",
  "name": "E2E Node Decision No Match",
  "steps": [
    {
      "id": "node-prepare-no-match",
      "name": "Prepare",
      "type": "SERVICE_TASK",
      "jobType": "node-prepare-no-match",
      "retryCount": 0,
      "nextStep": "node-route-no-match"
    },
    {
      "id": "node-route-no-match",
      "name": "Route",
      "type": "DECISION",
      "conditionalNextSteps": {
        "#result == 'approved'": "end"
      }
    },
    {
      "id": "end",
      "name": "End",
      "type": "END"
    }
  ]
}
